Workbook

Sheet データ
A1: 0 | D1: 総括 | E1: 県単河川維持工事(村田川草刈護岸工) | G1: 式 | H1: 1 | I1: 20500000 | J1: 20500000 | K1: 1
A2: 1 | D2: 内訳書 | E2: 準備工 | G2: 式 | H2: 1 | I2: 234000 | J2: 234000 | K2: 1 | M2: 54号内訳書
A3: 2 | B3: r20718007 | D3: 労務費 | E3: 運転工 | F3: 8H | G3: 人 | H3: 8 | I3: 23000 | J3: 184000 | K3: 1
A4: 2 | B4: k20718001 | D4: 機械費 | E4: 小物機械 ﾊﾟｰﾄﾅ・丸ﾉｺ | F4: ｸﾞﾗｲﾝﾀﾞ-・ｺｱ抜きﾄﾞﾘﾙ・ﾌﾞﾛｱ 等 | G4: 台 | H4: 2 | I4: 3000 | J4: 6000 | K4: 1
A5: 2 | B5: u20718025 | D5: 運搬費 | E5: 2tダンプ | G5: 台 | H5: 4 | I5: 6000 | J5: 24000 | K5: 1
A6: 2 | B6: u20718014 | D6: 運搬費 | E6: ４ｔユニック | G6: /日 | H6: 2 | I6: 10000 | J6: 20000 | K6: 1
A7: 1 | D7: 内訳書 | E7: 根固め工 | G7: 式 | H7: 1 | I7: 836000 | J7: 836000 | K7: 1 | M7: 15号内訳書
A8: 2 | D8: 内訳代価 | E8: 割栗石 | F8: 根固めブロック工 材料 | G8: 袋 | H8: 76 | K8: 76 | M8: 16号内訳書
A9: 3 | B9: s20718545 | D9: 材料費 | E9: 大型土嚢 | F9: ﾉｰﾏﾙ | G9: 袋 | H9: 80 | K9: 1
A10: 3 | D10: 材料費 | E10: 土嚢運搬費 | G10: 回 | H10: 1 | K10: 1
A11: 3 | B11: 1-5-32-3590-1 | D11: 材料費 | E11: 割ぐり石 | F11: 径150~200mm | G11: m3 | H11: 50 | K11: 1
A12: 3 | D12: 材料費 | E12: 袋詰め機械 | G12: 式 | H12: 1 | K12: 1
A13: 3 | B13: s20718549 | D13: 材料費 | E13: 軽油 | G13: L | H13: 0 | I13: 160 | K13: 1
A14: 3 | B14: k20718126 | D14: 機械費 | E14: ラフタークレーン25t | G14: 日台 | H14: 2 | K14: 1
A15: 3 | B15: s20718001 | D15: 材料費 | E15: 雑材 | G15: 式 | H15: 0 | I15: 280 | K15: 1
A16: 2 | D16: 内訳代価 | E16: 割栗石 | F16: 根固めブロック工 労務 機械 | G16: 袋 | H16: 76 | I16: 11000 | J16: 836000 | K16: 76 | M16: 43号内訳書
A17: 3 | B17: s20718001 | D17: 材料費 | E17: 雑材 | G17: 式 | H17: 1 | I17: 14000 | J17: 14000 | K17: 1
A18: 3 | B18: r20718007 | D18: 労務費 | E18: 運転工 | F18: 8H | G18: 人 | H18: 24 | I18: 23000 | J18: 552000 | K18: 1
A19: 3 | B19: k20718020 | D19: 機械費 | E19: BH0.45クレーン | F19: 低騒音・超小 | G19: 日台 | H19: 6 | I19: 14000 | J19: 84000 | K19: 1
A20: 3 | B20: k20718020 | D20: 機械費 | E20: BH0.45クレーン | F20: 低騒音・超小 | G20: 日台 | H20: 6 | I20: 14000 | J20: 84000 | K20: 1
A21: 3 | B21: k20718001 | D21: 機械費 | E21: 小物機械 ﾊﾟｰﾄﾅ・丸ﾉｺ | F21: ｸﾞﾗｲﾝﾀﾞ-・ｺｱ抜きﾄﾞﾘﾙ・ﾌﾞﾛｱ 等 | G21: 台 | H21: 6 | I21: 5000 | J21: 30000 | K21: 1
A22: 3 | B22: u20718025 | D22: 運搬費 | E22: 2tダンプ | G22: 台 | H22: 12 | I22: 6000 | J22: 72000 | K22: 1
A23: 1 | D23: 内訳書 | E23: 仮設工 | G23: 式 | H23: 1 | I23: 6515170 | J23: 6515170 | K23: 1 | M23: 17号内訳書
A24: 2 | D24: 内訳代価 | E24: 工事用道路盛土 | F24: ストックヤードから運搬 材料費 | G24: m3 | H24: 540 | K24: 400 | M24: 18号内訳書
A25: 3 | B25: s20718549 | D25: 材料費 | E25: 軽油 | G25: L | H25: 300 | K25: 1
A26: 3 | B26: s20718001 | D26: 材料費 | E26: 雑材 | G26: 式 | H26: 1 | K26: 1
A27: 3 | B27: k20718145 | D27: 機械費 | E27: 敷き鉄板リース5*10 | F27: 1500*3000*22 | G27: 式 | H27: 1 | K27: 1
A28: 3 | B28: u20718014 | D28: 運搬費 | E28: ４ｔユニック | G28: /日 | H28: 3 | K28: 1
A29: 2 | D29: 内訳代価 | E29: 工事用道路盛土 | F29: 施工幅2.5～4.0未満 労務機械 | G29: m3 | H29: 400 | I29: 2800 | J29: 1120000 | K29: 400 | M29: 44号内訳書
A30: 3 | B30: s20718001 | D30: 材料費 | E30: 雑材 | G30: 式 | H30: 0.741 | I30: 32000 | J30: 23712 | K30: 1
A31: 3 | B31: r20718007 | D31: 労務費 | E31: 運転工 | F31: 8H | G31: 人 | H31: 29.63 | I31: 23000 | J31: 681490 | K31: 1 | Z31: 10日×4人
A32: 3 | B32: k20718014 | D32: 機械費 | E32: BH0.15クレーン | F32: 低騒音・超小 | G32: 日台 | H32: 7.407 | I32: 11000 | J32: 81477 | K32: 1 | Z32: 10日×1台
A33: 3 | B33: k20718018 | D33: 機械費 | E33: BH0.25クレーン | F33: 低騒音・超小 | G33: 日台 | H33: 7.407 | I33: 11000 | J33: 81477 | K33: 1 | Z33: 10日×1台
A34: 3 | B34: k20718020 | D34: 機械費 | E34: BH0.45クレーン | F34: 低騒音・超小 | G34: 日台 | H34: 7.407 | I34: 14000 | J34: 103698 | K34: 1 | Z34: 10日×1台
A35: 3 | D35: 機械費 | E35: 法面バケット | F35: BH0.25用 | G35: /日 | H35: 7.407 | I35: 5000 | J35: 37035 | K35: 1 | Z35: 10日×1台
A36: 3 | B36: k20718001 | D36: 機械費 | E36: 小物機械 ﾊﾟｰﾄﾅ・丸ﾉｺ | F36: ｸﾞﾗｲﾝﾀﾞ-・ｺｱ抜きﾄﾞﾘﾙ・ﾌﾞﾛｱ 等 | G36: 台 | H36: 7.407 | I36: 3000 | J36: 22221 | K36: 1 | Z36: 10日×1台
A37: 3 | B37: u20718025 | D37: 運搬費 | E37: 2tダンプ | G37: 台 | H37: 14.815 | I37: 6000 | J37: 88890 | K37: 1 | Z37: 10日×2台
A38: 2 | D38: 内訳代価 | E38: 土嚢 | F38: 材料費 | G38: 袋 | H38: 85 | K38: 85 | M38: 19号内訳書
A39: 3 | B39: s20718544 | D39: 材料費 | E39: 土嚢袋 | G39: 袋 | H39: 85 | K39: 1
A40: 3 | B40: s20718549 | D40: 材料費 | E40: 軽油 | G40: L | H40: 200 | K40: 1
A41: 3 | B41: s20718001 | D41: 材料費 | E41: 雑材 | G41: 式 | H41: 1 | K41: 1
A42: 2 | D42: 内訳代価 | E42: 土嚢 | F42: 労務機械 | G42: 袋 | H42: 85 | I42: 3160 | J42: 268600 | K42: 85 | M42: 45号内訳書
A43: 3 | B43: s20718001 | D43: 材料費 | E43: 雑材 | G43: 式 | H43: 0.548 | I43: 17800 | J43: 9754 | K43: 1
A44: 3 | B44: r20718007 | D44: 労務費 | E44: 運転工 | F44: 8H | G44: 人 | H44: 8.774 | I44: 23000 | J44: 201802 | K44: 1 | Z44: 4日×4人
A45: 3 | B45: k20718018 | D45: 機械費 | E45: BH0.25クレーン | F45: 低騒音・超小 | G45: 日台 | H45: 2.194 | I45: 11000 | J45: 24134 | K45: 1 | Z45: 4日×4台
A46: 3 | B46: k20718001 | D46: 機械費 | E46: 小物機械 ﾊﾟｰﾄﾅ・丸ﾉｺ | F46: ｸﾞﾗｲﾝﾀﾞ-・ｺｱ抜きﾄﾞﾘﾙ・ﾌﾞﾛｱ 等 | G46: 台 | H46: 2.196 | I46: 3000 | J46: 6588 | K46: 1 | Z46: 4日×4台
A47: 3 | B47: u20718025 | D47: 運搬費 | E47: 2tダンプ | G47: 台 | H47: 4.387 | I47: 6000 | J47: 26322 | K47: 1 | Z47: 4日×2台
A48: 2 | D48: 内訳代価 | E48: 土砂運搬 | F48: ストックヤードから運搬 | G48: m3 | H48: 540 | I48: 1000 | J48: 540000 | K48: 540 | M48: 20号内訳書
A49: 3 | B49: s20718001 | D49: 材料費 | E49: 雑材 | G49: 式 | H49: 1 | K49: 1
A50: 3 | B50: s20718549 | D50: 材料費 | E50: 軽油 | G50: L | H50: 150 | K50: 1
A51: 3 | B51: u20718005 | D51: 運搬費 | E51: ダンプトラック常用8t | F51: オペ燃料付き | G51: 台 | H51: 10 | I51: 40000 | J51: 400000 | K51: 1
A52: 3 | B52: u20718001 | D52: 運搬費 | E52: ダンプトラック常用4t | F52: オペ燃料付き | G52: 日台 | H52: 4 | I52: 35000 | J52: 140000 | K52: 1
A53: 2 | D53: 内訳代価 | E53: 土砂運搬 労務機械 | F53: ストックヤードから運搬 | G53: m3 | H53: 540 | I53: 800 | J53: 432000 | K53: 540 | M53: 46号内訳書
A54: 3 | B54: s20718001 | D54: 材料費 | E54: 雑材 | G54: 式 | H54: 1 | I54: 12000 | J54: 12000 | K54: 1
A55: 3 | B55: r20718007 | D55: 労務費 | E55: 運転工 | F55: 8H | G55: 人 | H55: 10 | I55: 23000 | J55: 230000 | K55: 1 | Z55: 10日×4人
A56: 3 | B56: k20718018 | D56: 機械費 | E56: BH0.25クレーン | F56: 低騒音・超小 | G56: 日台 | H56: 10 | I56: 11000 | J56: 110000 | K56: 1 | Z56: 10日×4台
A57: 3 | B57: u0003 | D57: 運搬費 | E57: 4tﾀﾞﾝﾌﾟ | G57: 台 | H57: 10 | I57: 8000 | J57: 80000 | K57: 1 | Z57: 10日×4台
A58: 2 | D58: 内訳代価 | E58: 敷鉄板 | F58: 設置撤去5×10 | G58: m2 | H58: 497 | K58: 497 | M58: 21号内訳書
A59: 3 | B59: s20718001 | D59: 材料費 | E59: 雑材 | G59: 式 | H59: 1 | K59: 1
A60: 3 | B60: s20718002 | D60: 材料費 | E60: 燃料 軽油 | G60: L | H60: 200 | K60: 1
A61: 3 | B61: k20718145 | D61: 機械費 | E61: 敷き鉄板リース5*10 | F61: 1500*3000*22 | G61: 枚日 | H61: 110 | K61: 1
A62: 3 | B62: k20718145 | D62: 機械費 | E62: 敷き鉄板リース5*10 | F62: 1500*3000*22 基本料 | G62: 枚日 | H62: 110 | K62: 1
A63: 3 | B63: u20718013 | D63: 運搬費 | E63: 回送 トレーラー | G63: 回 | H63: 8 | K63: 1
A64: 2 | D64: 内訳代価 | E64: 敷鉄板 | F64: 設置撤去5×10 労務 | G64: m2 | H64: 497 | I64: 2310 | J64: 1148070 | K64: 497 | M64: 47号内訳書
A65: 3 | B65: s20718001 | D65: 材料費 | E65: 雑材 | G65: 式 | H65: 1 | I65: 4070 | J65: 4070 | K65: 1
A66: 3 | B66: r20718007 | D66: 労務費 | E66: 運転工 | F66: 8H | G66: 人 | H66: 32 | I66: 23000 | J66: 736000 | K66: 1 | Z66: 8日×4人
A67: 3 | B67: k20718018 | D67: 機械費 | E67: BH0.25クレーン | F67: 低騒音・超小 | G67: 日台 | H67: 8 | I67: 11000 | J67: 88000 | K67: 1 | Z67: 8日×1台
A68: 3 | B68: k20718020 | D68: 機械費 | E68: BH0.45クレーン | F68: 低騒音・超小 | G68: 日台 | H68: 8 | I68: 14000 | J68: 112000 | K68: 1 | Z68: 8日×1台
A69: 3 | B69: k20718020 | D69: 機械費 | E69: BH0.45クレーン | F69: 低騒音・超小 | G69: 日台 | H69: 8 | I69: 14000 | J69: 112000 | K69: 1 | Z69: 8日×1台
A70: 3 | B70: u20718025 | D70: 運搬費 | E70: 2tダンプ | G70: 台 | H70: 16 | I70: 6000 | J70: 96000 | K70: 1 | Z70: 8日×2台
A71: 2 | D71: 内訳代価 | E71: 工事用道路撤去 | F71: 燃料費 | G71: m3 | H71: 540 | K71: 540 | M71: 48号内訳書
A72: 3 | B72: s20718549 | D72: 材料費 | E72: 軽油 | G72: L | H72: 1000 | K72: 1
A73: 3 | B73: s20718001 | D73: 材料費 | E73: 雑材 | G73: 式 | H73: 1 | K73: 1
A74: 2 | D74: 内訳代価 | E74: 工事用道路撤去 | F74: 労務機械 | G74: m3 | H74: 540 | I74: 4100 | J74: 2214000 | K74: 540 | M74: 22号内訳書
A75: 3 | B75: s20718001 | D75: 材料費 | E75: 雑材 | G75: 式 | H75: 1 | I75: 9000 | J75: 9000 | K75: 1
A76: 3 | B76: r20718007 | D76: 労務費 | E76: 運転工 | F76: 8H | G76: 人 | H76: 60 | I76: 23000 | J76: 1380000 | K76: 1 | Z76: 15日×4人
A77: 3 | B77: k20718020 | D77: 機械費 | E77: BH0.45クレーン | F77: 低騒音・超小 | G77: 日台 | H77: 15 | I77: 14000 | J77: 210000 | K77: 1 | Z77: 15日×1台
A78: 3 | B78: k20718018 | D78: 機械費 | E78: BH0.25クレーン | F78: 低騒音・超小 | G78: 日台 | H78: 15 | I78: 11000 | J78: 165000 | K78: 1 | Z78: 15日×1台
A79: 3 | B79: k20718014 | D79: 機械費 | E79: BH0.15クレーン | F79: 低騒音・超小 | G79: 日台 | H79: 15 | I79: 7000 | J79: 105000 | K79: 1 | Z79: 15日×1台
A80: 3 | D80: 機械費 | E80: 法面バケット | F80: BH0.25用 | G80: /日 | H80: 15 | I80: 5000 | J80: 75000 | K80: 1 | Z80: 15日×1台
A81: 3 | D81: 機械費 | E81: 法面バケット | F81: BH0.15用 | G81: /日 | H81: 15 | I81: 3000 | J81: 45000 | K81: 1 | Z81: 15日×1台
A82: 3 | B82: k20718001 | D82: 機械費 | E82: 小物機械 ﾊﾟｰﾄﾅ・丸ﾉｺ | F82: ｸﾞﾗｲﾝﾀﾞ-・ｺｱ抜きﾄﾞﾘﾙ・ﾌﾞﾛｱ 等 | G82: 台 | H82: 15 | I82: 3000 | J82: 45000 | K82: 1 | Z82: 15日×1台
A83: 3 | B83: u20718025 | D83: 運搬費 | E83: 2tダンプ | G83: 台 | H83: 30 | I83: 6000 | J83: 180000 | K83: 1 | Z83: 15日×2台
A84: 2 | D84: 内訳代価 | E84: 土のう撤去 | G84: 袋 | H84: 85 | I84: 1700 | J84: 144500 | K84: 85 | M84: 24号内訳書
A85: 3 | B85: s20718001 | D85: 材料費 | E85: 雑材 | G85: 式 | H85: 0.548 | I85: 11500 | J85: 6302 | K85: 1
A86: 3 | B86: r20718007 | D86: 労務費 | E86: 運転工 | F86: 8H | G86: 人 | H86: 4.387 | I86: 23000 | J86: 100901 | K86: 1 | Z86: 2日×4人
A87: 3 | B87: k20718020 | D87: 機械費 | E87: BH0.45クレーン | F87: 低騒音・超小 | G87: 日台 | H87: 1.097 | I87: 14000 | J87: 15358 | K87: 1 | Z87: 2日×4台
A88: 3 | B88: k20718018 | D88: 機械費 | E88: BH0.25クレーン | F88: 低騒音・超小 | G88: 日台 | H88: 1.097 | I88: 11000 | J88: 12067 | K88: 1 | Z88: 2日×4台
A89: 3 | B89: k20718001 | D89: 機械費 | E89: 小物機械 ﾊﾟｰﾄﾅ・丸ﾉｺ | F89: ｸﾞﾗｲﾝﾀﾞ-・ｺｱ抜きﾄﾞﾘﾙ・ﾌﾞﾛｱ 等 | G89: 台 | H89: 1.097 | I89: 3000 | J89: 3291 | K89: 1 | Z89: 2日×4台
A90: 3 | B90: u20718025 | D90: 運搬費 | E90: 2tダンプ | G90: 台 | H90: 1.097 | I90: 6000 | J90: 6582 | K90: 1 | Z90: 2日×4台
A91: 2 | D91: 内訳代価 | E91: 産業廃棄物処分費 | G91: m3 | H91: 10 | K91: 10 | M91: 49号内訳書
A92: 3 | B92: u20718048 | D92: 運搬費 | E92: 産廃運搬処分 | G92: m3 | H92: 10 | K92: 1
A93: 2 | D93: 内訳代価 | E93: 土砂運搬 | F93: 8tDT 運搬 | G93: m3 | H93: 540 | K93: 540 | M93: 25号内訳書
A94: 3 | B94: s20718001 | D94: 材料費 | E94: 雑材 | G94: 式 | H94: 1 | K94: 1
A95: 3 | B95: s20718549 | D95: 材料費 | E95: 軽油 | G95: L | H95: 155 | K95: 1
A96: 2 | D96: 内訳代価 | E96: 土砂運搬 | F96: 8tDT 労務機械 | G96: m3 | H96: 540 | I96: 1200 | J96: 648000 | K96: 540 | M96: 50号内訳書
A97: 3 | B97: s20718001 | D97: 材料費 | E97: 雑材 | G97: 式 | H97: 1 | I97: 18000 | J97: 18000 | K97: 1
A98: 3 | B98: r20718007 | D98: 労務費 | E98: 運転工 | F98: 8H | G98: 人 | H98: 15 | I98: 23000 | J98: 345000 | K98: 1 | Z98: 15日×1人
A99: 3 | B99: k20718018 | D99: 機械費 | E99: BH0.25クレーン | F99: 低騒音・超小 | G99: 日台 | H99: 15 | I99: 11000 | J99: 165000 | K99: 1 | Z99: 瀬又置き場 15日×1台
A100: 3 | B100: u0003 | D100: 運搬費 | E100: 4tﾀﾞﾝﾌﾟ | G100: 台 | H100: 15 | I100: 8000 | J100: 120000 | K100: 1 | Z100: 15日×1台
...

Sheet 内訳一覧
D1: =D4 -> 県単河川維持工事(村田川草刈護岸工) | H1: 工事価格 | I1: 25300000 | J1: =I4/I$1 -> 0.81027668 | L1: 3 | P1: 工事価格 | R1: =Q4/Q$1 -> #DIV/0! | T1: 3 | X1: 工事価格 | Z1: =Y4/Y$1 -> #DIV/0! | AB1: 3
A2: 階層 | B2: 原価工種コード | C2: 帳票 | D2: 工種・種別・細別 | E2: 規格 | F2: 単位 | G2: 予算2 | O2: 予算 #02 | W2: 予算 #03 | AE2: ユーザー コード | AF2: 備考
G3: 数量 | H3: 単価 | I3: 金額 | J3: 当り数量 | L3: 構成率 | M3: 業者名 | N3: 摘要 | O3: 数量 | P3: 単価 | Q3: 金額 | R3: 当り数量 | T3: 構成率 | U3: 業者名 | V3: 摘要 | W3: 数量 | X3: 単価 | Y3: 金額 | Z3: 当り数量 | AB3: 構成率 | AC3: 業者名 | AD3: 摘要
A4: =データ!A1 -> 0 | B4: =TRIM(データ!C1) | C4: =TRIM(データ!D1) -> 総括 | D4: =REPT("｜",$A4)&TRIM(データ!E1) -> 県単河川維持工事(村田川草刈護岸工) | E4: =TRIM(データ!F1) | F4: =TRIM(データ!G1) -> 式 | G4: =データ!H1 -> 1 | H4: =データ!I1 -> 20500000 | I4: =データ!J1 -> 20500000 | J4: =IF(OR($C4="総括",$C4="内訳書",$C4="内訳代価",$C4="明細書",$C4="明細代価",$C4="代価表",$C4="単価表"),データ!K1,"") -> 1 | K4: =IF(OR(J4="",G4=J4),"","*") | L4: =IF($A4<=L$1,I4/I$4,"") -> 1 | M4: =IF(データ!L1="","",データ!L1) | N4: =IF(データ!M1="","",データ!M1) | O4: =データ!N1 -> 0 | P4: =IF($C4="集計行","",データ!O1) -> 0 | Q4: =データ!P1 -> 0 | R4: =IF(OR($C4="総括",$C4="内訳書",$C4="内訳代価",$C4="明細書",$C4="明細代価",$C4="代価表",$C4="単価表"),データ!Q1,"") -> 0 | S4: =IF(OR(R4="",O4=R4),"","*") | T4: =IF($A4<=T$1,Q4/Q$4,"") -> #DIV/0! | U4: =IF(データ!R1="","",データ!R1) | V4: =IF(データ!S1="","",データ!S1) | W4: =データ!T1 -> 0 | X4: =IF($C4="集計行","",データ!U1) -> 0 | Y4: =データ!V1 -> 0 | Z4: =IF(OR($C4="総括",$C4="内訳書",$C4="内訳代価",$C4="明細書",$C4="明細代価",$C4="代価表",$C4="単価表"),データ!W1,"") -> 0 | AA4: =IF(OR(Z4="",W4=Z4),"","*") | AB4: =IF($A4<=AB$1,Y4/Y$4,"") -> #DIV/0! | AC4: =IF(データ!X1="","",データ!X1) | AD4: =IF(データ!Y1="","",データ!Y1) | AE4: =TRIM(データ!B1) | AF4: =TRIM(データ!Z1)
A5: =データ!A2 -> 1 | B5: =TRIM(データ!C2) | C5: =TRIM(データ!D2) -> 内訳書 | D5: =REPT("｜",$A5)&TRIM(データ!E2) -> ｜準備工 | E5: =TRIM(データ!F2) | F5: =TRIM(データ!G2) -> 式 | G5: =データ!H2 -> 1 | H5: =データ!I2 -> 234000 | I5: =データ!J2 -> 234000 | J5: =IF(OR($C5="総括",$C5="内訳書",$C5="内訳代価",$C5="明細書",$C5="明細代価",$C5="代価表",$C5="単価表"),データ!K2,"") -> 1 | K5: =IF(OR(J5="",G5=J5),"","*") | L5: =IF($A5<=L$1,I5/I$4,"") -> 0.011414634 | M5: =IF(データ!L2="","",データ!L2) | N5: =IF(データ!M2="","",データ!M2) -> 54号内訳書 | O5: =データ!N2 -> 0 | P5: =IF($C5="集計行","",データ!O2) -> 0 | Q5: =データ!P2 -> 0 | R5: =IF(OR($C5="総括",$C5="内訳書",$C5="内訳代価",$C5="明細書",$C5="明細代価",$C5="代価表",$C5="単価表"),データ!Q2,"") -> 0 | S5: =IF(OR(R5="",O5=R5),"","*") | T5: =IF($A5<=T$1,Q5/Q$4,"") -> #DIV/0! | U5: =IF(データ!R2="","",データ!R2) | V5: =IF(データ!S2="","",データ!S2) | W5: =データ!T2 -> 0 | X5: =IF($C5="集計行","",データ!U2) -> 0 | Y5: =データ!V2 -> 0 | Z5: =IF(OR($C5="総括",$C5="内訳書",$C5="内訳代価",$C5="明細書",$C5="明細代価",$C5="代価表",$C5="単価表"),データ!W2,"") -> 0 | AA5: =IF(OR(Z5="",W5=Z5),"","*") | AB5: =IF($A5<=AB$1,Y5/Y$4,"") -> #DIV/0! | AC5: =IF(データ!X2="","",データ!X2) | AD5: =IF(データ!Y2="","",データ!Y2) | AE5: =TRIM(データ!B2) | AF5: =TRIM(データ!Z2)
A6: =データ!A3 -> 2 | B6: =TRIM(データ!C3) | C6: =TRIM(データ!D3) -> 労務費 | D6: =REPT("｜",$A6)&TRIM(データ!E3) -> ｜｜運転工 | E6: =TRIM(データ!F3) -> 8H | F6: =TRIM(データ!G3) -> 人 | G6: =データ!H3 -> 8 | H6: =データ!I3 -> 23000 | I6: =データ!J3 -> 184000 | J6: =IF(OR($C6="総括",$C6="内訳書",$C6="内訳代価",$C6="明細書",$C6="明細代価",$C6="代価表",$C6="単価表"),データ!K3,"") | K6: =IF(OR(J6="",G6=J6),"","*") | L6: =IF($A6<=L$1,I6/I$4,"") -> 0.0089756098 | M6: =IF(データ!L3="","",データ!L3) | N6: =IF(データ!M3="","",データ!M3) | O6: =データ!N3 -> 0 | P6: =IF($C6="集計行","",データ!O3) -> 0 | Q6: =データ!P3 -> 0 | R6: =IF(OR($C6="総括",$C6="内訳書",$C6="内訳代価",$C6="明細書",$C6="明細代価",$C6="代価表",$C6="単価表"),データ!Q3,"") | S6: =IF(OR(R6="",O6=R6),"","*") | T6: =IF($A6<=T$1,Q6/Q$4,"") -> #DIV/0! | U6: =IF(データ!R3="","",データ!R3) | V6: =IF(データ!S3="","",データ!S3) | W6: =データ!T3 -> 0 | X6: =IF($C6="集計行","",データ!U3) -> 0 | Y6: =データ!V3 -> 0 | Z6: =IF(OR($C6="総括",$C6="内訳書",$C6="内訳代価",$C6="明細書",$C6="明細代価",$C6="代価表",$C6="単価表"),データ!W3,"") | AA6: =IF(OR(Z6="",W6=Z6),"","*") | AB6: =IF($A6<=AB$1,Y6/Y$4,"") -> #DIV/0! | AC6: =IF(データ!X3="","",データ!X3) | AD6: =IF(データ!Y3="","",データ!Y3) | AE6: =TRIM(データ!B3) -> r20718007 | AF6: =TRIM(データ!Z3)
A7: =データ!A4 -> 2 | B7: =TRIM(データ!C4) | C7: =TRIM(データ!D4) -> 機械費 | D7: =REPT("｜",$A7)&TRIM(データ!E4) -> ｜｜小物機械 ﾊﾟｰﾄﾅ・丸ﾉｺ | E7: =TRIM(データ!F4) -> ｸﾞﾗｲﾝﾀﾞ-・ｺｱ抜きﾄﾞﾘﾙ・ﾌﾞﾛｱ 等 | F7: =TRIM(データ!G4) -> 台 | G7: =データ!H4 -> 2 | H7: =データ!I4 -> 3000 | I7: =データ!J4 -> 6000 | J7: =IF(OR($C7="総括",$C7="内訳書",$C7="内訳代価",$C7="明細書",$C7="明細代価",$C7="代価表",$C7="単価表"),データ!K4,"") | K7: =IF(OR(J7="",G7=J7),"","*") | L7: =IF($A7<=L$1,I7/I$4,"") -> 0.00029268293 | M7: =IF(データ!L4="","",データ!L4) | N7: =IF(データ!M4="","",データ!M4) | O7: =データ!N4 -> 0 | P7: =IF($C7="集計行","",データ!O4) -> 0 | Q7: =データ!P4 -> 0 | R7: =IF(OR($C7="総括",$C7="内訳書",$C7="内訳代価",$C7="明細書",$C7="明細代価",$C7="代価表",$C7="単価表"),データ!Q4,"") | S7: =IF(OR(R7="",O7=R7),"","*") | T7: =IF($A7<=T$1,Q7/Q$4,"") -> #DIV/0! | U7: =IF(データ!R4="","",データ!R4) | V7: =IF(データ!S4="","",データ!S4) | W7: =データ!T4 -> 0 | X7: =IF($C7="集計行","",データ!U4) -> 0 | Y7: =データ!V4 -> 0 | Z7: =IF(OR($C7="総括",$C7="内訳書",$C7="内訳代価",$C7="明細書",$C7="明細代価",$C7="代価表",$C7="単価表"),データ!W4,"") | AA7: =IF(OR(Z7="",W7=Z7),"","*") | AB7: =IF($A7<=AB$1,Y7/Y$4,"") -> #DIV/0! | AC7: =IF(データ!X4="","",データ!X4) | AD7: =IF(データ!Y4="","",データ!Y4) | AE7: =TRIM(データ!B4) -> k20718001 | AF7: =TRIM(データ!Z4)
A8: =データ!A5 -> 2 | B8: =TRIM(データ!C5) | C8: =TRIM(データ!D5) -> 運搬費 | D8: =REPT("｜",$A8)&TRIM(データ!E5) -> ｜｜2tダンプ | E8: =TRIM(データ!F5) | F8: =TRIM(データ!G5) -> 台 | G8: =データ!H5 -> 4 | H8: =データ!I5 -> 6000 | I8: =データ!J5 -> 24000 | J8: =IF(OR($C8="総括",$C8="内訳書",$C8="内訳代価",$C8="明細書",$C8="明細代価",$C8="代価表",$C8="単価表"),データ!K5,"") | K8: =IF(OR(J8="",G8=J8),"","*") | L8: =IF($A8<=L$1,I8/I$4,"") -> 0.0011707317 | M8: =IF(データ!L5="","",データ!L5) | N8: =IF(データ!M5="","",データ!M5) | O8: =データ!N5 -> 0 | P8: =IF($C8="集計行","",データ!O5) -> 0 | Q8: =データ!P5 -> 0 | R8: =IF(OR($C8="総括",$C8="内訳書",$C8="内訳代価",$C8="明細書",$C8="明細代価",$C8="代価表",$C8="単価表"),データ!Q5,"") | S8: =IF(OR(R8="",O8=R8),"","*") | T8: =IF($A8<=T$1,Q8/Q$4,"") -> #DIV/0! | U8: =IF(データ!R5="","",データ!R5) | V8: =IF(データ!S5="","",データ!S5) | W8: =データ!T5 -> 0 | X8: =IF($C8="集計行","",データ!U5) -> 0 | Y8: =データ!V5 -> 0 | Z8: =IF(OR($C8="総括",$C8="内訳書",$C8="内訳代価",$C8="明細書",$C8="明細代価",$C8="代価表",$C8="単価表"),データ!W5,"") | AA8: =IF(OR(Z8="",W8=Z8),"","*") | AB8: =IF($A8<=AB$1,Y8/Y$4,"") -> #DIV/0! | AC8: =IF(データ!X5="","",データ!X5) | AD8: =IF(データ!Y5="","",データ!Y5) | AE8: =TRIM(データ!B5) -> u20718025 | AF8: =TRIM(データ!Z5)
A9: =データ!A6 -> 2 | B9: =TRIM(データ!C6) | C9: =TRIM(データ!D6) -> 運搬費 | D9: =REPT("｜",$A9)&TRIM(データ!E6) -> ｜｜４ｔユニック | E9: =TRIM(データ!F6) | F9: =TRIM(データ!G6) -> /日 | G9: =データ!H6 -> 2 | H9: =データ!I6 -> 10000 | I9: =データ!J6 -> 20000 | J9: =IF(OR($C9="総括",$C9="内訳書",$C9="内訳代価",$C9="明細書",$C9="明細代価",$C9="代価表",$C9="単価表"),データ!K6,"") | K9: =IF(OR(J9="",G9=J9),"","*") | L9: =IF($A9<=L$1,I9/I$4,"") -> 0.00097560976 | M9: =IF(データ!L6="","",データ!L6) | N9: =IF(データ!M6="","",データ!M6) | O9: =データ!N6 -> 0 | P9: =IF($C9="集計行","",データ!O6) -> 0 | Q9: =データ!P6 -> 0 | R9: =IF(OR($C9="総括",$C9="内訳書",$C9="内訳代価",$C9="明細書",$C9="明細代価",$C9="代価表",$C9="単価表"),データ!Q6,"") | S9: =IF(OR(R9="",O9=R9),"","*") | T9: =IF($A9<=T$1,Q9/Q$4,"") -> #DIV/0! | U9: =IF(データ!R6="","",データ!R6) | V9: =IF(データ!S6="","",データ!S6) | W9: =データ!T6 -> 0 | X9: =IF($C9="集計行","",データ!U6) -> 0 | Y9: =データ!V6 -> 0 | Z9: =IF(OR($C9="総括",$C9="内訳書",$C9="内訳代価",$C9="明細書",$C9="明細代価",$C9="代価表",$C9="単価表"),データ!W6,"") | AA9: =IF(OR(Z9="",W9=Z9),"","*") | AB9: =IF($A9<=AB$1,Y9/Y$4,"") -> #DIV/0! | AC9: =IF(データ!X6="","",データ!X6) | AD9: =IF(データ!Y6="","",データ!Y6) | AE9: =TRIM(データ!B6) -> u20718014 | AF9: =TRIM(データ!Z6)
A10: =データ!A7 -> 1 | B10: =TRIM(データ!C7) | C10: =TRIM(データ!D7) -> 内訳書 | D10: =REPT("｜",$A10)&TRIM(データ!E7) -> ｜根固め工 | E10: =TRIM(データ!F7) | F10: =TRIM(データ!G7) -> 式 | G10: =データ!H7 -> 1 | H10: =データ!I7 -> 836000 | I10: =データ!J7 -> 836000 | J10: =IF(OR($C10="総括",$C10="内訳書",$C10="内訳代価",$C10="明細書",$C10="明細代価",$C10="代価表",$C10="単価表"),データ!K7,"") -> 1 | K10: =IF(OR(J10="",G10=J10),"","*") | L10: =IF($A10<=L$1,I10/I$4,"") -> 0.040780488 | M10: =IF(データ!L7="","",データ!L7) | N10: =IF(データ!M7="","",データ!M7) -> 15号内訳書 | O10: =データ!N7 -> 0 | P10: =IF($C10="集計行","",データ!O7) -> 0 | Q10: =データ!P7 -> 0 | R10: =IF(OR($C10="総括",$C10="内訳書",$C10="内訳代価",$C10="明細書",$C10="明細代価",$C10="代価表",$C10="単価表"),データ!Q7,"") -> 0 | S10: =IF(OR(R10="",O10=R10),"","*") | T10: =IF($A10<=T$1,Q10/Q$4,"") -> #DIV/0! | U10: =IF(データ!R7="","",データ!R7) | V10: =IF(データ!S7="","",データ!S7) | W10: =データ!T7 -> 0 | X10: =IF($C10="集計行","",データ!U7) -> 0 | Y10: =データ!V7 -> 0 | Z10: =IF(OR($C10="総括",$C10="内訳書",$C10="内訳代価",$C10="明細書",$C10="明細代価",$C10="代価表",$C10="単価表"),データ!W7,"") -> 0 | AA10: =IF(OR(Z10="",W10=Z10),"","*") | AB10: =IF($A10<=AB$1,Y10/Y$4,"") -> #DIV/0! | AC10: =IF(データ!X7="","",データ!X7) | AD10: =IF(データ!Y7="","",データ!Y7) | AE10: =TRIM(データ!B7) | AF10: =TRIM(データ!Z7)
A11: =データ!A8 -> 2 | B11: =TRIM(データ!C8) | C11: =TRIM(データ!D8) -> 内訳代価 | D11: =REPT("｜",$A11)&TRIM(データ!E8) -> ｜｜割栗石 | E11: =TRIM(データ!F8) -> 根固めブロック工 材料 | F11: =TRIM(データ!G8) -> 袋 | G11: =データ!H8 -> 76 | H11: =データ!I8 -> 0 | I11: =データ!J8 -> 0 | J11: =IF(OR($C11="総括",$C11="内訳書",$C11="内訳代価",$C11="明細書",$C11="明細代価",$C11="代価表",$C11="単価表"),データ!K8,"") -> 76 | K11: =IF(OR(J11="",G11=J11),"","*") | L11: =IF($A11<=L$1,I11/I$4,"") -> 0 | M11: =IF(データ!L8="","",データ!L8) | N11: =IF(データ!M8="","",データ!M8) -> 16号内訳書 | O11: =データ!N8 -> 0 | P11: =IF($C11="集計行","",データ!O8) -> 0 | Q11: =データ!P8 -> 0 | R11: =IF(OR($C11="総括",$C11="内訳書",$C11="内訳代価",$C11="明細書",$C11="明細代価",$C11="代価表",$C11="単価表"),データ!Q8,"") -> 0 | S11: =IF(OR(R11="",O11=R11),"","*") | T11: =IF($A11<=T$1,Q11/Q$4,"") -> #DIV/0! | U11: =IF(データ!R8="","",データ!R8) | V11: =IF(データ!S8="","",データ!S8) | W11: =データ!T8 -> 0 | X11: =IF($C11="集計行","",データ!U8) -> 0 | Y11: =データ!V8 -> 0 | Z11: =IF(OR($C11="総括",$C11="内訳書",$C11="内訳代価",$C11="明細書",$C11="明細代価",$C11="代価表",$C11="単価表"),データ!W8,"") -> 0 | AA11: =IF(OR(Z11="",W11=Z11),"","*") | AB11: =IF($A11<=AB$1,Y11/Y$4,"") -> #DIV/0! | AC11: =IF(データ!X8="","",データ!X8) | AD11: =IF(データ!Y8="","",データ!Y8) | AE11: =TRIM(データ!B8) | AF11: =TRIM(データ!Z8)
A12: =データ!A9 -> 3 | B12: =TRIM(データ!C9) | C12: =TRIM(データ!D9) -> 材料費 | D12: =REPT("｜",$A12)&TRIM(データ!E9) -> ｜｜｜大型土嚢 | E12: =TRIM(データ!F9) -> ﾉｰﾏﾙ | F12: =TRIM(データ!G9) -> 袋 | G12: =データ!H9 -> 80 | H12: =データ!I9 -> 0 | I12: =データ!J9 -> 0 | J12: =IF(OR($C12="総括",$C12="内訳書",$C12="内訳代価",$C12="明細書",$C12="明細代価",$C12="代価表",$C12="単価表"),データ!K9,"") | K12: =IF(OR(J12="",G12=J12),"","*") | L12: =IF($A12<=L$1,I12/I$4,"") -> 0 | M12: =IF(データ!L9="","",データ!L9) | N12: =IF(データ!M9="","",データ!M9) | O12: =データ!N9 -> 0 | P12: =IF($C12="集計行","",データ!O9) -> 0 | Q12: =データ!P9 -> 0 | R12: =IF(OR($C12="総括",$C12="内訳書",$C12="内訳代価",$C12="明細書",$C12="明細代価",$C12="代価表",$C12="単価表"),データ!Q9,"") | S12: =IF(OR(R12="",O12=R12),"","*") | T12: =IF($A12<=T$1,Q12/Q$4,"") -> #DIV/0! | U12: =IF(データ!R9="","",データ!R9) | V12: =IF(データ!S9="","",データ!S9) | W12: =データ!T9 -> 0 | X12: =IF($C12="集計行","",データ!U9) -> 0 | Y12: =データ!V9 -> 0 | Z12: =IF(OR($C12="総括",$C12="内訳書",$C12="内訳代価",$C12="明細書",$C12="明細代価",$C12="代価表",$C12="単価表"),データ!W9,"") | AA12: =IF(OR(Z12="",W12=Z12),"","*") | AB12: =IF($A12<=AB$1,Y12/Y$4,"") -> #DIV/0! | AC12: =IF(データ!X9="","",データ!X9) | AD12: =IF(データ!Y9="","",データ!Y9) | AE12: =TRIM(データ!B9) -> s20718545 | AF12: =TRIM(データ!Z9)
A13: =データ!A10 -> 3 | B13: =TRIM(データ!C10) | C13: =TRIM(データ!D10) -> 材料費 | D13: =REPT("｜",$A13)&TRIM(データ!E10) -> ｜｜｜土嚢運搬費 | E13: =TRIM(データ!F10) | F13: =TRIM(データ!G10) -> 回 | G13: =データ!H10 -> 1 | H13: =データ!I10 -> 0 | I13: =データ!J10 -> 0 | J13: =IF(OR($C13="総括",$C13="内訳書",$C13="内訳代価",$C13="明細書",$C13="明細代価",$C13="代価表",$C13="単価表"),データ!K10,"") | K13: =IF(OR(J13="",G13=J13),"","*") | L13: =IF($A13<=L$1,I13/I$4,"") -> 0 | M13: =IF(データ!L10="","",データ!L10) | N13: =IF(データ!M10="","",データ!M10) | O13: =データ!N10 -> 0 | P13: =IF($C13="集計行","",データ!O10) -> 0 | Q13: =データ!P10 -> 0 | R13: =IF(OR($C13="総括",$C13="内訳書",$C13="内訳代価",$C13="明細書",$C13="明細代価",$C13="代価表",$C13="単価表"),データ!Q10,"") | S13: =IF(OR(R13="",O13=R13),"","*") | T13: =IF($A13<=T$1,Q13/Q$4,"") -> #DIV/0! | U13: =IF(データ!R10="","",データ!R10) | V13: =IF(データ!S10="","",データ!S10) | W13: =データ!T10 -> 0 | X13: =IF($C13="集計行","",データ!U10) -> 0 | Y13: =データ!V10 -> 0 | Z13: =IF(OR($C13="総括",$C13="内訳書",$C13="内訳代価",$C13="明細書",$C13="明細代価",$C13="代価表",$C13="単価表"),データ!W10,"") | AA13: =IF(OR(Z13="",W13=Z13),"","*") | AB13: =IF($A13<=AB$1,Y13/Y$4,"") -> #DIV/0! | AC13: =IF(データ!X10="","",データ!X10) | AD13: =IF(データ!Y10="","",データ!Y10) | AE13: =TRIM(データ!B10) | AF13: =TRIM(データ!Z10)
A14: =データ!A11 -> 3 | B14: =TRIM(データ!C11) | C14: =TRIM(データ!D11) -> 材料費 | D14: =REPT("｜",$A14)&TRIM(データ!E11) -> ｜｜｜割ぐり石 | E14: =TRIM(データ!F11) -> 径150~200mm | F14: =TRIM(データ!G11) -> m3 | G14: =データ!H11 -> 50 | H14: =データ!I11 -> 0 | I14: =データ!J11 -> 0 | J14: =IF(OR($C14="総括",$C14="内訳書",$C14="内訳代価",$C14="明細書",$C14="明細代価",$C14="代価表",$C14="単価表"),データ!K11,"") | K14: =IF(OR(J14="",G14=J14),"","*") | L14: =IF($A14<=L$1,I14/I$4,"") -> 0 | M14: =IF(データ!L11="","",データ!L11) | N14: =IF(データ!M11="","",データ!M11) | O14: =データ!N11 -> 0 | P14: =IF($C14="集計行","",データ!O11) -> 0 | Q14: =データ!P11 -> 0 | R14: =IF(OR($C14="総括",$C14="内訳書",$C14="内訳代価",$C14="明細書",$C14="明細代価",$C14="代価表",$C14="単価表"),データ!Q11,"") | S14: =IF(OR(R14="",O14=R14),"","*") | T14: =IF($A14<=T$1,Q14/Q$4,"") -> #DIV/0! | U14: =IF(データ!R11="","",データ!R11) | V14: =IF(データ!S11="","",データ!S11) | W14: =データ!T11 -> 0 | X14: =IF($C14="集計行","",データ!U11) -> 0 | Y14: =データ!V11 -> 0 | Z14: =IF(OR($C14="総括",$C14="内訳書",$C14="内訳代価",$C14="明細書",$C14="明細代価",$C14="代価表",$C14="単価表"),データ!W11,"") | AA14: =IF(OR(Z14="",W14=Z14),"","*") | AB14: =IF($A14<=AB$1,Y14/Y$4,"") -> #DIV/0! | AC14: =IF(データ!X11="","",データ!X11) | AD14: =IF(データ!Y11="","",データ!Y11) | AE14: =TRIM(データ!B11) -> 1-5-32-3590-1 | AF14: =TRIM(データ!Z11)
A15: =データ!A12 -> 3 | B15: =TRIM(データ!C12) | C15: =TRIM(データ!D12) -> 材料費 | D15: =REPT("｜",$A15)&TRIM(データ!E12) -> ｜｜｜袋詰め機械 | E15: =TRIM(データ!F12) | F15: =TRIM(データ!G12) -> 式 | G15: =データ!H12 -> 1 | H15: =データ!I12 -> 0 | I15: =データ!J12 -> 0 | J15: =IF(OR($C15="総括",$C15="内訳書",$C15="内訳代価",$C15="明細書",$C15="明細代価",$C15="代価表",$C15="単価表"),データ!K12,"") | K15: =IF(OR(J15="",G15=J15),"","*") | L15: =IF($A15<=L$1,I15/I$4,"") -> 0 | M15: =IF(データ!L12="","",データ!L12) | N15: =IF(データ!M12="","",データ!M12) | O15: =データ!N12 -> 0 | P15: =IF($C15="集計行","",データ!O12) -> 0 | Q15: =データ!P12 -> 0 | R15: =IF(OR($C15="総括",$C15="内訳書",$C15="内訳代価",$C15="明細書",$C15="明細代価",$C15="代価表",$C15="単価表"),データ!Q12,"") | S15: =IF(OR(R15="",O15=R15),"","*") | T15: =IF($A15<=T$1,Q15/Q$4,"") -> #DIV/0! | U15: =IF(データ!R12="","",データ!R12) | V15: =IF(データ!S12="","",データ!S12) | W15: =データ!T12 -> 0 | X15: =IF($C15="集計行","",データ!U12) -> 0 | Y15: =データ!V12 -> 0 | Z15: =IF(OR($C15="総括",$C15="内訳書",$C15="内訳代価",$C15="明細書",$C15="明細代価",$C15="代価表",$C15="単価表"),データ!W12,"") | AA15: =IF(OR(Z15="",W15=Z15),"","*") | AB15: =IF($A15<=AB$1,Y15/Y$4,"") -> #DIV/0! | AC15: =IF(データ!X12="","",データ!X12) | AD15: =IF(データ!Y12="","",データ!Y12) | AE15: =TRIM(データ!B12) | AF15: =TRIM(データ!Z12)
... A199: =データ!A196 -> 2 | B199: =TRIM(データ!C196) | C199: =TRIM(データ!D196) -> 機械費 | D199: =REPT("｜",$A199)&TRIM(データ!E196) -> ｜｜ランマー | E199: =TRIM(データ!F196) | F199: =TRIM(データ!G196) -> 日台 | G199: =データ!H196 -> 16 | H199: =データ!I196 -> 500 | I199: =データ!J196 -> 8000 | J199: =IF(OR($C199="総括",$C199="内訳書",$C199="内訳代価",$C199="明細書",$C199="明細代価",$C199="代価表",$C199="単価表"),データ!K196,"") | K199: =IF(OR(J199="",G199=J199),"","*") | L199: =IF($A199<=L$1,I199/I$4,"") -> 0.0003902439 | M199: =IF(データ!L196="","",データ!L196) | N199: =IF(データ!M196="","",データ!M196) | O199: =データ!N196 -> 0 | P199: =IF($C199="集計行","",データ!O196) -> 0 | Q199: =データ!P196 -> 0 | R199: =IF(OR($C199="総括",$C199="内訳書",$C199="内訳代価",$C199="明細書",$C199="明細代価",$C199="代価表",$C199="単価表"),データ!Q196,"") | S199: =IF(OR(R199="",O199=R199),"","*") | T199: =IF($A199<=T$1,Q199/Q$4,"") -> #DIV/0! | U199: =IF(データ!R196="","",データ!R196) | V199: =IF(データ!S196="","",データ!S196) | W199: =データ!T196 -> 0 | X199: =IF($C199="集計行","",データ!U196) -> 0 | Y199: =データ!V196 -> 0 | Z199: =IF(OR($C199="総括",$C199="内訳書",$C199="内訳代価",$C199="明細書",$C199="明細代価",$C199="代価表",$C199="単価表"),データ!W196,"") | AA199: =IF(OR(Z199="",W199=Z199),"","*") | AB199: =IF($A199<=AB$1,Y199/Y$4,"") -> #DIV/0! | AC199: =IF(データ!X196="","",データ!X196) | AD199: =IF(データ!Y196="","",データ!Y196) | AE199: =TRIM(データ!B196) -> k20718065 | AF199: =TRIM(データ!Z196)
